tson/__init__.py
tson/deserializer.py
tson/fileio.py
tson/prettify.py
tson/serializer.py
tson/utils.py
tson-1.1.0.dist-info/METADATA
tson-1.1.0.dist-info/WHEEL
tson-1.1.0.dist-info/top_level.txt
tson-1.1.0.dist-info/RECORD
