Metadata-Version: 2.4
Name: tson
Version: 1.1.0
Summary: Token-efficient Structured Object Notation for LLMs
Home-page: https://github.com/zenoaihq/tson
Author: Zeno AI
Author-email: shubham@zenoai.tech
Project-URL: Bug Reports, https://github.com/zenoaihq/tson/issues
Project-URL: Source, https://github.com/zenoaihq/tson
Project-URL: Documentation, https://github.com/zenoaihq/tson/blob/main/SPEC.md
Keywords: serialization,json,llm,tokens,efficiency,data-format,tson
Classifier: Development Status :: 4 - Beta
Classifier: Intended Audience :: Developers
Classifier: Topic :: Software Development :: Libraries :: Python Modules
Classifier: Topic :: Text Processing :: Markup
Classifier: License :: OSI Approved :: MIT License
Classifier: Programming Language :: Python :: 3
Classifier: Programming Language :: Python :: 3.7
Classifier: Programming Language :: Python :: 3.8
Classifier: Programming Language :: Python :: 3.9
Classifier: Programming Language :: Python :: 3.10
Classifier: Programming Language :: Python :: 3.11
Classifier: Programming Language :: Python :: 3.12
Requires-Python: >=3.7
Provides-Extra: dev
Requires-Dist: pytest>=7.0; extra == "dev"
Requires-Dist: pytest-cov>=4.0; extra == "dev"
Dynamic: author
Dynamic: author-email
Dynamic: classifier
Dynamic: description
Dynamic: description-content-type
Dynamic: home-page
Dynamic: keywords
Dynamic: project-url
Dynamic: provides-extra
Dynamic: requires-python
Dynamic: summary
